asicverifier/__init__.py
asicverifier/__main__.py
asicverifier/restful_api.py
AsicVerifier-0.2.4.dist-info/LICENSE
AsicVerifier-0.2.4.dist-info/METADATA
AsicVerifier-0.2.4.dist-info/WHEEL
AsicVerifier-0.2.4.dist-info/entry_points.txt
AsicVerifier-0.2.4.dist-info/top_level.txt
AsicVerifier-0.2.4.dist-info/RECORD
