Metadata-Version: 2.1
Name: AsicVerifier
Version: 0.2.4
Summary: Asic Verifier for X-Road
Home-page: https://github.com/pipinfitriadi/asicverifier
Author: Pipin Fitriadi
Author-email: pipinfitriadi@gmail.com
Maintainer: Pipin Fitriadi
Maintainer-email: pipinfitriadi@gmail.com
License: AGPL-3.0-only
Project-URL: Repository, https://github.com/pipinfitriadi/asicverifier
Project-URL: Docker, https://hub.docker.com/r/pipinfitriadi/asicverifier
Keywords: X-Road,security server
Classifier: Development Status :: 2 - Pre-Alpha
Classifier: Programming Language :: Java
Classifier: Programming Language :: Python :: 3.8
Classifier: License :: OSI Approved :: GNU Affero General Public License v3
Classifier: Operating System :: OS Independent
Classifier: Framework :: FastAPI
Classifier: Topic :: File Formats :: JSON
Classifier: Topic :: Internet :: WWW/HTTP :: HTTP Servers
Classifier: Topic :: Text Processing
Classifier: Topic :: Utilities
Requires-Python: >=3.8
License-File: LICENSE
Requires-Dist: python-dotenv
Requires-Dist: typer[all]
Requires-Dist: requests
Requires-Dist: python-dateutil
Requires-Dist: importlib-metadata
Provides-Extra: restful-api
Requires-Dist: pydantic[email] ; extra == 'restful-api'
Requires-Dist: fastapi ; extra == 'restful-api'
Requires-Dist: uvicorn[standard] ; extra == 'restful-api'
